README.md
setup.py
ggeocode/__init__.py
ggeocode/coder.py
ggeocode/iso3.py
ggeocode/parser.py
ggeocode.egg-info/PKG-INFO
ggeocode.egg-info/SOURCES.txt
ggeocode.egg-info/dependency_links.txt
ggeocode.egg-info/top_level.txt