Metadata-Version: 1.0
Name: ggeocode
Version: 0.1
Summary: Simple Python library for geocoding placenames to countries, using the free GeoNames dataset.
Home-page: UNKNOWN
Author: David Megginson
Author-email: megginson@un.org
License: UNKNOWN
Platform: UNKNOWN
